cfe/VERSION
cfe/__init__.py
cfe/df_utils.py
cfe/dgp.py
cfe/estimation.py
cfe/input_files.py
cfe/regression.py
cfe/requirements.txt
cfe/result.py
cfedemands-0.8.0.dist-info/licenses/LICENSE.txt
cfedemands-0.8.0.dist-info/METADATA
cfedemands-0.8.0.dist-info/WHEEL
cfedemands-0.8.0.dist-info/top_level.txt
cfedemands-0.8.0.dist-info/zip-safe
cfedemands-0.8.0.dist-info/RECORD
