Metadata-Version: 2.4
Name: CFEDemands
Version: 0.8.0
Summary: Tools for estimating and computing Constant Frisch Elasticity (CFE) demands.
Home-page: https://github.com/ligon/CFEDemands
Author-email: ligon@berkeley.edu
License: Creative Commons Attribution-Noncommercial-ShareAlike 4.0 International license
License-File: LICENSE.txt
Requires-Dist: ConsumerDemands>=0.3.dev0
Requires-Dist: matplotlib>=3.5.1
Requires-Dist: numpy>=1.21.5
Requires-Dist: pandas>=1.3.5
Requires-Dist: scipy>=1.7.3
Requires-Dist: importlib_metadata>=6.7.0
Requires-Dist: fsspec
Dynamic: license-file
